scanbook/__init__.py
scanbook/cli.py
scanbook/process.py
scanbook-0.1.1.dist-info/LICENSE
scanbook-0.1.1.dist-info/METADATA
scanbook-0.1.1.dist-info/WHEEL
scanbook-0.1.1.dist-info/entry_points.txt
scanbook-0.1.1.dist-info/top_level.txt
scanbook-0.1.1.dist-info/RECORD
