Metadata-Version: 2.1
Name: scanbook
Version: 0.1.1
Summary: Tool that processes page images for easier reading
Home-page: https://github.com/bencrowder/scanbook
Author: Ben Crowder
Author-email: ben.crowder@gmail.com
License: MIT
Platform: UNKNOWN
Classifier: Programming Language :: Python :: 3
Classifier: License :: OSI Approved :: MIT License
Classifier: Operating System :: OS Independent
Requires-Python: >=3.6
Requires-Dist: click
Requires-Dist: opencv-python
Requires-Dist: scikit-image
